escope/__init__.py
escope/escope.py
escope/espark.py
escope/loader.py
escope/peakx.py
escope/spikex.py
escope/units.py
escope/escopelib/Struct.py
escope/escopelib/__init__.py
escope/escopelib/eschannels.py
escope/escopelib/esconfig.py
escope/escopelib/esdatasource.py
escope/escopelib/esdsnidaq.py
escope/escopelib/esdspicodaq.py
escope/escopelib/esdsxxdaq.py
escope/escopelib/eshardware.py
escope/escopelib/esnidaq.py
escope/escopelib/esparkwin.py
escope/escopelib/espchannels.py
escope/escopelib/espconfig.py
escope/escopelib/espdatasink.py
escope/escopelib/espdsnidaq.py
escope/escopelib/espdspicodaq.py
escope/escopelib/espdsxxdaq.py
escope/escopelib/espgraph.py
escope/escopelib/esphardware.py
escope/escopelib/espicodaq.py
escope/escopelib/espmgraph.py
escope/escopelib/esppulsegraph.py
escope/escopelib/espqgraph.py
escope/escopelib/espsinks.py
escope/escopelib/esptraingraph.py
escope/escopelib/esptypebox.py
escope/escopelib/espvaredit.py
escope/escopelib/esscopewin.py
escope/escopelib/estmarks.py
escope/escopelib/estrigger.py
escope/escopelib/estriggerbuffer.py
escope/escopelib/esvscalemarks.py
escope/escopelib/esvzeromarks.py
escope/escopelib/ledlabel.py
escope/escopelib/picodaq_backend.py
escope/escopelib/serializer.py
escope-4.1.0.dist-info/licenses/LICENSE
escope-4.1.0.dist-info/METADATA
escope-4.1.0.dist-info/WHEEL
escope-4.1.0.dist-info/entry_points.txt
escope-4.1.0.dist-info/top_level.txt
escope-4.1.0.dist-info/RECORD
