Metadata-Version: 2.4
Name: escope
Version: 4.1.0
Summary: A software oscilloscope for electrophysiology
Author-email: "Daniel A. Wagenaar" <daw@caltech.edu>
Project-URL: Homepage, https://github.com/wagenadl/escope
Classifier: Programming Language :: Python :: 3
Classifier: License :: OSI Approved :: GNU General Public License v3 or later (GPLv3+)
Classifier: Operating System :: OS Independent
Requires-Python: >=3.10
License-File: LICENSE
Requires-Dist: pyqt5
Requires-Dist: numpy
Requires-Dist: numba==0.61.2
Requires-Dist: nidaqmx
Requires-Dist: pyqtgraph
Dynamic: license-file
